{
  "title": {
    "original": "A Haunted House 2",
    "german": "Ghost Movie 2"
  },
  "rating": {
    "total": 650
  },
  "dateSeen": "2019-12-27T23:00:00.000Z",
  "fsk": 16,
  "mm": false,
  "tmdbID": 184345,
  "releaseDate": "2014-04-17T00:00:00.000Z",
  "runtime": 87,
  "genres": [
    "Komödie",
    "Horror"
  ],
  "posterURL": "/gzwZYGnp4c4iO6yMw4pCxyJ4rMm.jpg",
  "budget": 4000000,
  "revenue": 25343661,
  "overview": "Neues Haus, neues Glück? Von wegen! Gerade ein Jahr sind die schrecklichen Ereignisse her, mit denen sich Malcolm und seine damalige Frau Kisha konfrontiert sehen mussten, als ein Poltergeist zuerst ihr Haus heimsuchte und schließlich von Kisha Besitz nahm. Kisha ist mittlerweile bei einem Autounfall ums Leben gekommen, aber dieses geht schließlich weiter und so hat Malcolm inzwischen Megan geheiratet. Mit ihr und ihren zwei Kindern aus erster Ehe zieht er in eine neue Wohnung weit weg von den Gräueln des letzten Jahres. Doch schon beim Einzug deuten gravierende Geschehnisse auf die Rückkehr des Paranormalen hin. Als schließlich die von den Toten zurückgekehrte Kisha ausgerechnet in die Nachbarschaft zieht, ist Schluss mit lustig und ein weiterer Exorzismus muss her. Und diesmal ein definitiver!"
}