{
  "title": {
    "original": "Ma",
    "german": "Ma - Sie sieht alles"
  },
  "rating": {
    "total": 625,
    "ch": 500,
    "rt": 750
  },
  "dateSeen": "2021-02-17T23:00:00.000Z",
  "fsk": 16,
  "tmdbID": 502416,
  "releaseDate": "2019-05-29T00:00:00.000Z",
  "runtime": 100,
  "genres": [
    "Horror",
    "Thriller"
  ],
  "posterURL": "/grNZP7eRYyXGlOSNVsaO0i7e3k5.jpg",
  "budget": 5000000,
  "revenue": 51749995,
  "overview": "Bei Ma sind alle willkommen. Es scheint ein glückliches Zusammentreffen zu sein: Sue Ann lebt einsam und allein in einem braven Kaff in Ohio. Neuankömmling Maggie und ihre Freunde wollen feiern - dürfen als Teenager aber noch keinen Alkohol kaufen. Also besorgt Sue Ann ihnen den Stoff. Und bietet den neuen, jugendlichen Freunden auch gleich noch ihren Keller als Partylocation an.  Doch es herrschen klare Regeln in Sue Anns Haus: Wer fährt, bleibt nüchtern! Keine Kraftausdrücke! Die oberen Stockwerke sind tabu! Und Sue Ann wird \"Ma\" genannt.  Bald entpuppt sich die vermeintliche Gastfreundschaft Mas als obsessive Gier nach Gesellschaft. Der scheinbare Teenager-Traum verwandelt sich zum grauenvollen Albtraum. Und Mas Haus wird vom heißesten Schuppen der Stadt zur Hölle auf Erden."
}