{
  "title": {
    "original": "언니",
    "german": "No Mercy - Nichts kann sie stoppen"
  },
  "tmdbID": 569016,
  "rating": {
    "total": 375
  },
  "dateSeen": "2019-08-16T00:00:00.000Z",
  "fsk": 18,
  "releaseDate": "2019-01-01T00:00:00.000Z",
  "runtime": 94,
  "genres": [
    "Action",
    "Krimi",
    "Thriller",
    "Mystery"
  ],
  "posterURL": "/nnKnIrNlVO1c6JWR8SwzgaAH19p.jpg",
  "budget": 0,
  "revenue": 0,
  "overview": "Als ihre Schwester Eunhye eines Tages nicht von der Schule zurückkehrt und weder Polizei noch Lehrer Interesse an dem Mysterium zeigen, nimmt Bodyguard Inae den Fall selbst auf. Dabei findet sie heraus, dass Eunhyes Mitschülerinnen dem Mädchen einen Streich gespielt haben, der jedoch schrecklich eskaliert ist und sie in einen Komplott von Verbrechern und Zuhältern geraten ist. Aus der Mission ihre Schwester zu retten, wird für Inae schon bald ein rücksichtsloser Rachefeldzug.",
  "mm": true,
  "slug": ""
}