{
  "title": {
    "original": "La piel que habito",
    "german": "Die Haut, in der ich wohne"
  },
  "rating": {
    "total": 625,
    "ch": 600,
    "rt": 650
  },
  "dateSeen": "2020-08-26T22:00:00.000Z",
  "fsk": 16,
  "tmdbID": 63311,
  "releaseDate": "2011-08-17T00:00:00.000Z",
  "runtime": 116,
  "genres": [
    "Drama",
    "Horror"
  ],
  "posterURL": "/csm7ImJJ0AkUivg3UlrpeE4bJuo.jpg",
  "budget": 13000000,
  "revenue": 33750478,
  "overview": "Vera wird in einer privaten Schönheitsklinik von dem Chirurgen Dr. Robert Ledgard überwacht. Das Besondere ist jedoch, das sie der einzige Patient in der gesamten Einrichtung ist. Einzig die Haushälterin Marilla und ein mysteriöser Mann in einem Tigerkostüm, wandeln in der Klinik umher. Was hat es mit Vera auf sich, deren Vergangenheit in dunklen Schatten liegt und deren Äußeres Dr. Ledgards verstorbener Frau ähnelt, diese aber dennoch nicht ist. Doch das sind nicht die einzigen Rätsel, die geklärt werden müssen …",
  "slug": "la-piel-que-habito"
}